README.md
setup.py
alibabacloud_tea_roa/__init__.py
alibabacloud_tea_roa/client.py
alibabacloud_tea_roa/models.py
alibabacloud_tea_roa.egg-info/PKG-INFO
alibabacloud_tea_roa.egg-info/SOURCES.txt
alibabacloud_tea_roa.egg-info/dependency_links.txt
alibabacloud_tea_roa.egg-info/requires.txt
alibabacloud_tea_roa.egg-info/top_level.txt